<?xml version="1.0" encoding="UTF-8" standalone="yes"?>
<p:sld xmlns:a="http://schemas.openxmlformats.org/drawingml/2006/main" xmlns:r="http://schemas.openxmlformats.org/officeDocument/2006/relationships" xmlns:p="http://schemas.openxmlformats.org/presentationml/2006/main"><p:cSld name="Slide 4"><p:bg><p:bgPr><a:solidFill><a:srgbClr val="F8F5F2"/></a:solidFill><a:effectLst/></p:bgPr></p:bg><p:spTree><p:nvGrpSpPr><p:cNvPr id="1" name=""/><p:cNvGrpSpPr/><p:nvPr/></p:nvGrpSpPr><p:grpSpPr><a:xfrm><a:off x="0" y="0"/><a:ext cx="0" cy="0"/><a:chOff x="0" y="0"/><a:chExt cx="0" cy="0"/></a:xfrm></p:grpSpPr><p:sp><p:nvSpPr><p:cNvPr id="2" name="Text 0"/><p:cNvSpPr/><p:nvPr/></p:nvSpPr><p:spPr><a:xfrm><a:off x="363940" y="363940"/><a:ext cx="11536907" cy="218364"/></a:xfrm><a:prstGeom prst="rect"><a:avLst/></a:prstGeom><a:noFill/><a:ln/></p:spPr><p:txBody><a:bodyPr wrap="square" lIns="0" tIns="0" rIns="0" bIns="0" rtlCol="0" anchor="ctr"/><a:lstStyle/><a:p><a:pPr><a:lnSpc><a:spcPct val="130000"/></a:lnSpc></a:pPr><a:r><a:rPr lang="en-US" sz="1146" b="1" kern="0" spc="57" dirty="0"><a:solidFill><a:srgbClr val="4DB6AC"/></a:solidFill><a:latin typeface="Liter" pitchFamily="34" charset="0"/><a:ea typeface="Liter" pitchFamily="34" charset="-122"/><a:cs typeface="Liter" pitchFamily="34" charset="-120"/></a:rPr><a:t>CAPABILITIES</a:t></a:r><a:endParaRPr lang="en-US" sz="1600" dirty="0"/></a:p></p:txBody></p:sp><p:sp><p:nvSpPr><p:cNvPr id="3" name="Text 1"/><p:cNvSpPr/><p:nvPr/></p:nvSpPr><p:spPr><a:xfrm><a:off x="363940" y="655093"/><a:ext cx="11682484" cy="436728"/></a:xfrm><a:prstGeom prst="rect"><a:avLst/></a:prstGeom><a:noFill/><a:ln/></p:spPr><p:txBody><a:bodyPr wrap="square" lIns="0" tIns="0" rIns="0" bIns="0" rtlCol="0" anchor="ctr"/><a:lstStyle/><a:p><a:pPr><a:lnSpc><a:spcPct val="80000"/></a:lnSpc></a:pPr><a:r><a:rPr lang="en-US" sz="3439" b="1" dirty="0"><a:solidFill><a:srgbClr val="3E3E3C"/></a:solidFill><a:latin typeface="Hedvig Letters Sans" pitchFamily="34" charset="0"/><a:ea typeface="Hedvig Letters Sans" pitchFamily="34" charset="-122"/><a:cs typeface="Hedvig Letters Sans" pitchFamily="34" charset="-120"/></a:rPr><a:t>Key Features</a:t></a:r><a:endParaRPr lang="en-US" sz="1600" dirty="0"/></a:p></p:txBody></p:sp><p:sp><p:nvSpPr><p:cNvPr id="4" name="Text 2"/><p:cNvSpPr/><p:nvPr/></p:nvSpPr><p:spPr><a:xfrm><a:off x="363940" y="1164609"/><a:ext cx="11555104" cy="254758"/></a:xfrm><a:prstGeom prst="rect"><a:avLst/></a:prstGeom><a:noFill/><a:ln/></p:spPr><p:txBody><a:bodyPr wrap="square" lIns="0" tIns="0" rIns="0" bIns="0" rtlCol="0" anchor="ctr"/><a:lstStyle/><a:p><a:pPr><a:lnSpc><a:spcPct val="120000"/></a:lnSpc></a:pPr><a:r><a:rPr lang="en-US" sz="1433" dirty="0"><a:solidFill><a:srgbClr val="3E3E3C"><a:alpha val="70000"/></a:srgbClr></a:solidFill><a:latin typeface="Liter" pitchFamily="34" charset="0"/><a:ea typeface="Liter" pitchFamily="34" charset="-122"/><a:cs typeface="Liter" pitchFamily="34" charset="-120"/></a:rPr><a:t>Comprehensive climate risk intelligence at your fingertips</a:t></a:r><a:endParaRPr lang="en-US" sz="1600" dirty="0"/></a:p></p:txBody></p:sp><p:sp><p:nvSpPr><p:cNvPr id="5" name="Shape 3"/><p:cNvSpPr/><p:nvPr/></p:nvSpPr><p:spPr><a:xfrm><a:off x="363940" y="1637731"/><a:ext cx="3703093" cy="2520287"/></a:xfrm><a:custGeom><a:avLst/><a:gdLst/><a:ahLst/><a:cxnLst/><a:rect l="l" t="t" r="r" b="b"/><a:pathLst><a:path w="3703093" h="2520287"><a:moveTo><a:pt x="218358" y="0"/></a:moveTo><a:lnTo><a:pt x="3484735" y="0"/></a:lnTo><a:cubicBezTo><a:pt x="3605250" y="0"/><a:pt x="3703093" y="97843"/><a:pt x="3703093" y="218358"/></a:cubicBezTo><a:lnTo><a:pt x="3703093" y="2301929"/></a:lnTo><a:cubicBezTo><a:pt x="3703093" y="2422444"/><a:pt x="3605250" y="2520287"/><a:pt x="3484735" y="2520287"/></a:cubicBezTo><a:lnTo><a:pt x="218358" y="2520287"/></a:lnTo><a:cubicBezTo><a:pt x="97843" y="2520287"/><a:pt x="0" y="2422444"/><a:pt x="0" y="2301929"/></a:cubicBezTo><a:lnTo><a:pt x="0" y="218358"/></a:lnTo><a:cubicBezTo><a:pt x="0" y="97843"/><a:pt x="97843" y="0"/><a:pt x="218358" y="0"/></a:cubicBezTo><a:close/></a:path></a:pathLst></a:custGeom><a:solidFill><a:srgbClr val="FFFFFF"/></a:solidFill><a:ln/><a:effectLst><a:outerShdw blurRad="136478" dist="90985" dir="5400000" algn="bl" rotWithShape="0"><a:srgbClr val="000000"><a:alpha val="7843"/></a:srgbClr></a:outerShdw></a:effectLst></p:spPr><p:txBody><a:bodyPr/><a:lstStyle/><a:p><a:endParaRPr lang="en-US"/></a:p></p:txBody></p:sp><p:sp><p:nvSpPr><p:cNvPr id="6" name="Shape 4"/><p:cNvSpPr/><p:nvPr/></p:nvSpPr><p:spPr><a:xfrm><a:off x="582304" y="1856096"/><a:ext cx="582304" cy="582304"/></a:xfrm><a:custGeom><a:avLst/><a:gdLst/><a:ahLst/><a:cxnLst/><a:rect l="l" t="t" r="r" b="b"/><a:pathLst><a:path w="582304" h="582304"><a:moveTo><a:pt x="145576" y="0"/></a:moveTo><a:lnTo><a:pt x="436728" y="0"/></a:lnTo><a:cubicBezTo><a:pt x="517074" y="0"/><a:pt x="582304" y="65230"/><a:pt x="582304" y="145576"/></a:cubicBezTo><a:lnTo><a:pt x="582304" y="436728"/></a:lnTo><a:cubicBezTo><a:pt x="582304" y="517074"/><a:pt x="517074" y="582304"/><a:pt x="436728" y="582304"/></a:cubicBezTo><a:lnTo><a:pt x="145576" y="582304"/></a:lnTo><a:cubicBezTo><a:pt x="65230" y="582304"/><a:pt x="0" y="517074"/><a:pt x="0" y="436728"/></a:cubicBezTo><a:lnTo><a:pt x="0" y="145576"/></a:lnTo><a:cubicBezTo><a:pt x="0" y="65230"/><a:pt x="65230" y="0"/><a:pt x="145576" y="0"/></a:cubicBezTo><a:close/></a:path></a:pathLst></a:custGeom><a:gradFill flip="none" rotWithShape="1"><a:gsLst><a:gs pos="0"><a:srgbClr val="4DB6AC"/></a:gs><a:gs pos="100000"><a:srgbClr val="3D9A91"/></a:gs></a:gsLst><a:lin ang="2700000" scaled="1"/></a:gradFill><a:ln/><a:effectLst><a:outerShdw blurRad="54591" dist="36394" dir="5400000" algn="bl" rotWithShape="0"><a:srgbClr val="4DB6AC"><a:alpha val="30196"/></a:srgbClr></a:outerShdw></a:effectLst></p:spPr><p:txBody><a:bodyPr/><a:lstStyle/><a:p><a:endParaRPr lang="en-US"/></a:p></p:txBody></p:sp><p:sp><p:nvSpPr><p:cNvPr id="7" name="Shape 5"/><p:cNvSpPr/><p:nvPr/></p:nvSpPr><p:spPr><a:xfrm><a:off x="739254" y="2010770"/><a:ext cx="272955" cy="272955"/></a:xfrm><a:custGeom><a:avLst/><a:gdLst/><a:ahLst/><a:cxnLst/><a:rect l="l" t="t" r="r" b="b"/><a:pathLst><a:path w="272955" h="272955"><a:moveTo><a:pt x="136478" y="255896"/></a:moveTo><a:cubicBezTo><a:pt x="211860" y="255896"/><a:pt x="272955" y="198586"/><a:pt x="272955" y="127948"/></a:cubicBezTo><a:cubicBezTo><a:pt x="272955" y="57310"/><a:pt x="211860" y="0"/><a:pt x="136478" y="0"/></a:cubicBezTo><a:cubicBezTo><a:pt x="61095" y="0"/><a:pt x="0" y="57310"/><a:pt x="0" y="127948"/></a:cubicBezTo><a:cubicBezTo><a:pt x="0" y="156896"/><a:pt x="10236" y="183552"/><a:pt x="27509" y="204983"/></a:cubicBezTo><a:lnTo><a:pt x="1493" y="254190"/></a:lnTo><a:cubicBezTo><a:pt x="-1066" y="258988"/><a:pt x="-267" y="264852"/><a:pt x="3412" y="268850"/></a:cubicBezTo><a:cubicBezTo><a:pt x="7090" y="272849"/><a:pt x="12901" y="274075"/><a:pt x="17859" y="271942"/></a:cubicBezTo><a:lnTo><a:pt x="80980" y="244913"/></a:lnTo><a:cubicBezTo><a:pt x="97933" y="251950"/><a:pt x="116699" y="255896"/><a:pt x="136478" y="255896"/></a:cubicBezTo><a:close/><a:moveTo><a:pt x="68239" y="110888"/></a:moveTo><a:cubicBezTo><a:pt x="77654" y="110888"/><a:pt x="85299" y="118532"/><a:pt x="85299" y="127948"/></a:cubicBezTo><a:cubicBezTo><a:pt x="85299" y="137363"/><a:pt x="77654" y="145007"/><a:pt x="68239" y="145007"/></a:cubicBezTo><a:cubicBezTo><a:pt x="58823" y="145007"/><a:pt x="51179" y="137363"/><a:pt x="51179" y="127948"/></a:cubicBezTo><a:cubicBezTo><a:pt x="51179" y="118532"/><a:pt x="58823" y="110888"/><a:pt x="68239" y="110888"/></a:cubicBezTo><a:close/><a:moveTo><a:pt x="136478" y="110888"/></a:moveTo><a:cubicBezTo><a:pt x="145893" y="110888"/><a:pt x="153537" y="118532"/><a:pt x="153537" y="127948"/></a:cubicBezTo><a:cubicBezTo><a:pt x="153537" y="137363"/><a:pt x="145893" y="145007"/><a:pt x="136478" y="145007"/></a:cubicBezTo><a:cubicBezTo><a:pt x="127062" y="145007"/><a:pt x="119418" y="137363"/><a:pt x="119418" y="127948"/></a:cubicBezTo><a:cubicBezTo><a:pt x="119418" y="118532"/><a:pt x="127062" y="110888"/><a:pt x="136478" y="110888"/></a:cubicBezTo><a:close/><a:moveTo><a:pt x="187657" y="127948"/></a:moveTo><a:cubicBezTo><a:pt x="187657" y="118532"/><a:pt x="195301" y="110888"/><a:pt x="204716" y="110888"/></a:cubicBezTo><a:cubicBezTo><a:pt x="214132" y="110888"/><a:pt x="221776" y="118532"/><a:pt x="221776" y="127948"/></a:cubicBezTo><a:cubicBezTo><a:pt x="221776" y="137363"/><a:pt x="214132" y="145007"/><a:pt x="204716" y="145007"/></a:cubicBezTo><a:cubicBezTo><a:pt x="195301" y="145007"/><a:pt x="187657" y="137363"/><a:pt x="187657" y="127948"/></a:cubicBezTo><a:close/></a:path></a:pathLst></a:custGeom><a:solidFill><a:srgbClr val="FFFFFF"/></a:solidFill><a:ln/></p:spPr><p:txBody><a:bodyPr/><a:lstStyle/><a:p><a:endParaRPr lang="en-US"/></a:p></p:txBody></p:sp><p:sp><p:nvSpPr><p:cNvPr id="8" name="Text 6"/><p:cNvSpPr/><p:nvPr/></p:nvSpPr><p:spPr><a:xfrm><a:off x="582304" y="2583976"/><a:ext cx="3375546" cy="291152"/></a:xfrm><a:prstGeom prst="rect"><a:avLst/></a:prstGeom><a:noFill/><a:ln/></p:spPr><p:txBody><a:bodyPr wrap="square" lIns="0" tIns="0" rIns="0" bIns="0" rtlCol="0" anchor="ctr"/><a:lstStyle/><a:p><a:pPr><a:lnSpc><a:spcPct val="110000"/></a:lnSpc></a:pPr><a:r><a:rPr lang="en-US" sz="1719" b="1" dirty="0"><a:solidFill><a:srgbClr val="3E3E3C"/></a:solidFill><a:latin typeface="Hedvig Letters Sans" pitchFamily="34" charset="0"/><a:ea typeface="Hedvig Letters Sans" pitchFamily="34" charset="-122"/><a:cs typeface="Hedvig Letters Sans" pitchFamily="34" charset="-120"/></a:rPr><a:t>Chat-Based UI</a:t></a:r><a:endParaRPr lang="en-US" sz="1600" dirty="0"/></a:p></p:txBody></p:sp><p:sp><p:nvSpPr><p:cNvPr id="9" name="Text 7"/><p:cNvSpPr/><p:nvPr/></p:nvSpPr><p:spPr><a:xfrm><a:off x="582304" y="2984197"/><a:ext cx="3339152" cy="473122"/></a:xfrm><a:prstGeom prst="rect"><a:avLst/></a:prstGeom><a:noFill/><a:ln/></p:spPr><p:txBody><a:bodyPr wrap="square" lIns="0" tIns="0" rIns="0" bIns="0" rtlCol="0" anchor="ctr"/><a:lstStyle/><a:p><a:pPr><a:lnSpc><a:spcPct val="140000"/></a:lnSpc></a:pPr><a:r><a:rPr lang="en-US" sz="1146" dirty="0"><a:solidFill><a:srgbClr val="3E3E3C"><a:alpha val="70000"/></a:srgbClr></a:solidFill><a:latin typeface="Liter" pitchFamily="34" charset="0"/><a:ea typeface="Liter" pitchFamily="34" charset="-122"/><a:cs typeface="Liter" pitchFamily="34" charset="-120"/></a:rPr><a:t>Natural language interface for intuitive queries. No technical expertise required.</a:t></a:r><a:endParaRPr lang="en-US" sz="1600" dirty="0"/></a:p></p:txBody></p:sp><p:sp><p:nvSpPr><p:cNvPr id="10" name="Shape 8"/><p:cNvSpPr/><p:nvPr/></p:nvSpPr><p:spPr><a:xfrm><a:off x="582304" y="3606535"/><a:ext cx="3266364" cy="7279"/></a:xfrm><a:custGeom><a:avLst/><a:gdLst/><a:ahLst/><a:cxnLst/><a:rect l="l" t="t" r="r" b="b"/><a:pathLst><a:path w="3266364" h="7279"><a:moveTo><a:pt x="0" y="0"/></a:moveTo><a:lnTo><a:pt x="3266364" y="0"/></a:lnTo><a:lnTo><a:pt x="3266364" y="7279"/></a:lnTo><a:lnTo><a:pt x="0" y="7279"/></a:lnTo><a:lnTo><a:pt x="0" y="0"/></a:lnTo><a:close/></a:path></a:pathLst></a:custGeom><a:solidFill><a:srgbClr val="4DB6AC"><a:alpha val="20000"/></a:srgbClr></a:solidFill><a:ln/></p:spPr><p:txBody><a:bodyPr/><a:lstStyle/><a:p><a:endParaRPr lang="en-US"/></a:p></p:txBody></p:sp><p:sp><p:nvSpPr><p:cNvPr id="11" name="Text 9"/><p:cNvSpPr/><p:nvPr/></p:nvSpPr><p:spPr><a:xfrm><a:off x="582304" y="3755751"/><a:ext cx="3330054" cy="181970"/></a:xfrm><a:prstGeom prst="rect"><a:avLst/></a:prstGeom><a:noFill/><a:ln/></p:spPr><p:txBody><a:bodyPr wrap="square" lIns="0" tIns="0" rIns="0" bIns="0" rtlCol="0" anchor="ctr"/><a:lstStyle/><a:p><a:pPr><a:lnSpc><a:spcPct val="120000"/></a:lnSpc></a:pPr><a:r><a:rPr lang="en-US" sz="1003" b="1" dirty="0"><a:solidFill><a:srgbClr val="4DB6AC"/></a:solidFill><a:latin typeface="Liter" pitchFamily="34" charset="0"/><a:ea typeface="Liter" pitchFamily="34" charset="-122"/><a:cs typeface="Liter" pitchFamily="34" charset="-120"/></a:rPr><a:t>✓ Zero learning curve</a:t></a:r><a:endParaRPr lang="en-US" sz="1600" dirty="0"/></a:p></p:txBody></p:sp><p:sp><p:nvSpPr><p:cNvPr id="12" name="Shape 10"/><p:cNvSpPr/><p:nvPr/></p:nvSpPr><p:spPr><a:xfrm><a:off x="4247297" y="1637731"/><a:ext cx="3703093" cy="2520287"/></a:xfrm><a:custGeom><a:avLst/><a:gdLst/><a:ahLst/><a:cxnLst/><a:rect l="l" t="t" r="r" b="b"/><a:pathLst><a:path w="3703093" h="2520287"><a:moveTo><a:pt x="218358" y="0"/></a:moveTo><a:lnTo><a:pt x="3484735" y="0"/></a:lnTo><a:cubicBezTo><a:pt x="3605250" y="0"/><a:pt x="3703093" y="97843"/><a:pt x="3703093" y="218358"/></a:cubicBezTo><a:lnTo><a:pt x="3703093" y="2301929"/></a:lnTo><a:cubicBezTo><a:pt x="3703093" y="2422444"/><a:pt x="3605250" y="2520287"/><a:pt x="3484735" y="2520287"/></a:cubicBezTo><a:lnTo><a:pt x="218358" y="2520287"/></a:lnTo><a:cubicBezTo><a:pt x="97843" y="2520287"/><a:pt x="0" y="2422444"/><a:pt x="0" y="2301929"/></a:cubicBezTo><a:lnTo><a:pt x="0" y="218358"/></a:lnTo><a:cubicBezTo><a:pt x="0" y="97843"/><a:pt x="97843" y="0"/><a:pt x="218358" y="0"/></a:cubicBezTo><a:close/></a:path></a:pathLst></a:custGeom><a:solidFill><a:srgbClr val="FFFFFF"/></a:solidFill><a:ln/><a:effectLst><a:outerShdw blurRad="136478" dist="90985" dir="5400000" algn="bl" rotWithShape="0"><a:srgbClr val="000000"><a:alpha val="7843"/></a:srgbClr></a:outerShdw></a:effectLst></p:spPr><p:txBody><a:bodyPr/><a:lstStyle/><a:p><a:endParaRPr lang="en-US"/></a:p></p:txBody></p:sp><p:sp><p:nvSpPr><p:cNvPr id="13" name="Shape 11"/><p:cNvSpPr/><p:nvPr/></p:nvSpPr><p:spPr><a:xfrm><a:off x="4465661" y="1856096"/><a:ext cx="582304" cy="582304"/></a:xfrm><a:custGeom><a:avLst/><a:gdLst/><a:ahLst/><a:cxnLst/><a:rect l="l" t="t" r="r" b="b"/><a:pathLst><a:path w="582304" h="582304"><a:moveTo><a:pt x="145576" y="0"/></a:moveTo><a:lnTo><a:pt x="436728" y="0"/></a:lnTo><a:cubicBezTo><a:pt x="517074" y="0"/><a:pt x="582304" y="65230"/><a:pt x="582304" y="145576"/></a:cubicBezTo><a:lnTo><a:pt x="582304" y="436728"/></a:lnTo><a:cubicBezTo><a:pt x="582304" y="517074"/><a:pt x="517074" y="582304"/><a:pt x="436728" y="582304"/></a:cubicBezTo><a:lnTo><a:pt x="145576" y="582304"/></a:lnTo><a:cubicBezTo><a:pt x="65230" y="582304"/><a:pt x="0" y="517074"/><a:pt x="0" y="436728"/></a:cubicBezTo><a:lnTo><a:pt x="0" y="145576"/></a:lnTo><a:cubicBezTo><a:pt x="0" y="65230"/><a:pt x="65230" y="0"/><a:pt x="145576" y="0"/></a:cubicBezTo><a:close/></a:path></a:pathLst></a:custGeom><a:solidFill><a:srgbClr val="FFB74D"/></a:solidFill><a:ln/><a:effectLst><a:outerShdw blurRad="136478" dist="90985" dir="5400000" algn="bl" rotWithShape="0"><a:srgbClr val="000000"><a:alpha val="10196"/></a:srgbClr></a:outerShdw></a:effectLst></p:spPr><p:txBody><a:bodyPr/><a:lstStyle/><a:p><a:endParaRPr lang="en-US"/></a:p></p:txBody></p:sp><p:sp><p:nvSpPr><p:cNvPr id="14" name="Shape 12"/><p:cNvSpPr/><p:nvPr/></p:nvSpPr><p:spPr><a:xfrm><a:off x="4639670" y="2010770"/><a:ext cx="238836" cy="272955"/></a:xfrm><a:custGeom><a:avLst/><a:gdLst/><a:ahLst/><a:cxnLst/><a:rect l="l" t="t" r="r" b="b"/><a:pathLst><a:path w="238836" h="272955"><a:moveTo><a:pt x="85565" y="-14074"/></a:moveTo><a:cubicBezTo><a:pt x="90523" y="-18233"/><a:pt x="97827" y="-18073"/><a:pt x="102571" y="-13594"/></a:cubicBezTo><a:cubicBezTo><a:pt x="109129" y="-7410"/><a:pt x="114993" y="-586"/><a:pt x="120644" y="6344"/></a:cubicBezTo><a:cubicBezTo><a:pt x="127841" y="15140"/><a:pt x="136478" y="26762"/><a:pt x="144794" y="40570"/></a:cubicBezTo><a:cubicBezTo><a:pt x="147566" y="36945"/><a:pt x="150125" y="33746"/><a:pt x="152364" y="31027"/></a:cubicBezTo><a:cubicBezTo><a:pt x="152951" y="30334"/><a:pt x="153537" y="29588"/><a:pt x="154124" y="28842"/></a:cubicBezTo><a:cubicBezTo><a:pt x="158335" y="23617"/><a:pt x="163560" y="17060"/><a:pt x="170544" y="17060"/></a:cubicBezTo><a:cubicBezTo><a:pt x="177687" y="17060"/><a:pt x="182699" y="23404"/><a:pt x="186964" y="28842"/></a:cubicBezTo><a:cubicBezTo><a:pt x="187657" y="29748"/><a:pt x="188350" y="30601"/><a:pt x="189043" y="31401"/></a:cubicBezTo><a:cubicBezTo><a:pt x="194534" y="38011"/><a:pt x="201838" y="47554"/><a:pt x="209141" y="59336"/></a:cubicBezTo><a:cubicBezTo><a:pt x="223642" y="82740"/><a:pt x="238783" y="116059"/><a:pt x="238783" y="153484"/></a:cubicBezTo><a:cubicBezTo><a:pt x="238783" y="219430"/><a:pt x="185311" y="272902"/><a:pt x="119365" y="272902"/></a:cubicBezTo><a:cubicBezTo><a:pt x="53418" y="272902"/><a:pt x="0" y="219484"/><a:pt x="0" y="153537"/></a:cubicBezTo><a:cubicBezTo><a:pt x="0" y="104970"/><a:pt x="21911" y="62908"/><a:pt x="42916" y="33586"/></a:cubicBezTo><a:cubicBezTo><a:pt x="53525" y="18819"/><a:pt x="64081" y="6984"/><a:pt x="72024" y="-1120"/></a:cubicBezTo><a:cubicBezTo><a:pt x="76395" y="-5598"/><a:pt x="80820" y="-10023"/><a:pt x="85618" y="-14021"/></a:cubicBezTo><a:close/><a:moveTo><a:pt x="120324" y="221776"/></a:moveTo><a:cubicBezTo><a:pt x="133812" y="221776"/><a:pt x="145754" y="218044"/><a:pt x="157003" y="210581"/></a:cubicBezTo><a:cubicBezTo><a:pt x="179447" y="194907"/><a:pt x="185471" y="163560"/><a:pt x="171983" y="138930"/></a:cubicBezTo><a:cubicBezTo><a:pt x="169584" y="134132"/><a:pt x="163453" y="133812"/><a:pt x="159988" y="137864"/></a:cubicBezTo><a:lnTo><a:pt x="146553" y="153484"/></a:lnTo><a:cubicBezTo><a:pt x="143035" y="157536"/><a:pt x="136691" y="157429"/><a:pt x="133386" y="153217"/></a:cubicBezTo><a:cubicBezTo><a:pt x="124163" y="141436"/><a:pt x="107210" y="119951"/><a:pt x="98573" y="108969"/></a:cubicBezTo><a:cubicBezTo><a:pt x="95694" y="105290"/><a:pt x="90470" y="104704"/><a:pt x="87111" y="107956"/></a:cubicBezTo><a:cubicBezTo><a:pt x="77355" y="117445"/><a:pt x="59656" y="138237"/><a:pt x="59656" y="163560"/></a:cubicBezTo><a:cubicBezTo><a:pt x="59656" y="200132"/><a:pt x="86631" y="221776"/><a:pt x="120271" y="221776"/></a:cubicBezTo><a:close/></a:path></a:pathLst></a:custGeom><a:solidFill><a:srgbClr val="FFFFFF"/></a:solidFill><a:ln/></p:spPr><p:txBody><a:bodyPr/><a:lstStyle/><a:p><a:endParaRPr lang="en-US"/></a:p></p:txBody></p:sp><p:sp><p:nvSpPr><p:cNvPr id="15" name="Text 13"/><p:cNvSpPr/><p:nvPr/></p:nvSpPr><p:spPr><a:xfrm><a:off x="4465661" y="2583976"/><a:ext cx="3375546" cy="291152"/></a:xfrm><a:prstGeom prst="rect"><a:avLst/></a:prstGeom><a:noFill/><a:ln/></p:spPr><p:txBody><a:bodyPr wrap="square" lIns="0" tIns="0" rIns="0" bIns="0" rtlCol="0" anchor="ctr"/><a:lstStyle/><a:p><a:pPr><a:lnSpc><a:spcPct val="110000"/></a:lnSpc></a:pPr><a:r><a:rPr lang="en-US" sz="1719" b="1" dirty="0"><a:solidFill><a:srgbClr val="3E3E3C"/></a:solidFill><a:latin typeface="Hedvig Letters Sans" pitchFamily="34" charset="0"/><a:ea typeface="Hedvig Letters Sans" pitchFamily="34" charset="-122"/><a:cs typeface="Hedvig Letters Sans" pitchFamily="34" charset="-120"/></a:rPr><a:t>Risk Visualization</a:t></a:r><a:endParaRPr lang="en-US" sz="1600" dirty="0"/></a:p></p:txBody></p:sp><p:sp><p:nvSpPr><p:cNvPr id="16" name="Text 14"/><p:cNvSpPr/><p:nvPr/></p:nvSpPr><p:spPr><a:xfrm><a:off x="4465661" y="2984197"/><a:ext cx="3339152" cy="473122"/></a:xfrm><a:prstGeom prst="rect"><a:avLst/></a:prstGeom><a:noFill/><a:ln/></p:spPr><p:txBody><a:bodyPr wrap="square" lIns="0" tIns="0" rIns="0" bIns="0" rtlCol="0" anchor="ctr"/><a:lstStyle/><a:p><a:pPr><a:lnSpc><a:spcPct val="140000"/></a:lnSpc></a:pPr><a:r><a:rPr lang="en-US" sz="1146" dirty="0"><a:solidFill><a:srgbClr val="3E3E3C"><a:alpha val="70000"/></a:srgbClr></a:solidFill><a:latin typeface="Liter" pitchFamily="34" charset="0"/><a:ea typeface="Liter" pitchFamily="34" charset="-122"/><a:cs typeface="Liter" pitchFamily="34" charset="-120"/></a:rPr><a:t>Interactive heatmaps for flood and heat risk with real-time overlays.</a:t></a:r><a:endParaRPr lang="en-US" sz="1600" dirty="0"/></a:p></p:txBody></p:sp><p:sp><p:nvSpPr><p:cNvPr id="17" name="Shape 15"/><p:cNvSpPr/><p:nvPr/></p:nvSpPr><p:spPr><a:xfrm><a:off x="4465661" y="3606535"/><a:ext cx="3266364" cy="7279"/></a:xfrm><a:custGeom><a:avLst/><a:gdLst/><a:ahLst/><a:cxnLst/><a:rect l="l" t="t" r="r" b="b"/><a:pathLst><a:path w="3266364" h="7279"><a:moveTo><a:pt x="0" y="0"/></a:moveTo><a:lnTo><a:pt x="3266364" y="0"/></a:lnTo><a:lnTo><a:pt x="3266364" y="7279"/></a:lnTo><a:lnTo><a:pt x="0" y="7279"/></a:lnTo><a:lnTo><a:pt x="0" y="0"/></a:lnTo><a:close/></a:path></a:pathLst></a:custGeom><a:solidFill><a:srgbClr val="FFB74D"><a:alpha val="20000"/></a:srgbClr></a:solidFill><a:ln/></p:spPr><p:txBody><a:bodyPr/><a:lstStyle/><a:p><a:endParaRPr lang="en-US"/></a:p></p:txBody></p:sp><p:sp><p:nvSpPr><p:cNvPr id="18" name="Text 16"/><p:cNvSpPr/><p:nvPr/></p:nvSpPr><p:spPr><a:xfrm><a:off x="4465661" y="3755751"/><a:ext cx="3330054" cy="181970"/></a:xfrm><a:prstGeom prst="rect"><a:avLst/></a:prstGeom><a:noFill/><a:ln/></p:spPr><p:txBody><a:bodyPr wrap="square" lIns="0" tIns="0" rIns="0" bIns="0" rtlCol="0" anchor="ctr"/><a:lstStyle/><a:p><a:pPr><a:lnSpc><a:spcPct val="120000"/></a:lnSpc></a:pPr><a:r><a:rPr lang="en-US" sz="1003" b="1" dirty="0"><a:solidFill><a:srgbClr val="FFB74D"/></a:solidFill><a:latin typeface="Liter" pitchFamily="34" charset="0"/><a:ea typeface="Liter" pitchFamily="34" charset="-122"/><a:cs typeface="Liter" pitchFamily="34" charset="-120"/></a:rPr><a:t>✓ Visual decision support</a:t></a:r><a:endParaRPr lang="en-US" sz="1600" dirty="0"/></a:p></p:txBody></p:sp><p:sp><p:nvSpPr><p:cNvPr id="19" name="Shape 17"/><p:cNvSpPr/><p:nvPr/></p:nvSpPr><p:spPr><a:xfrm><a:off x="8130654" y="1637731"/><a:ext cx="3703093" cy="2520287"/></a:xfrm><a:custGeom><a:avLst/><a:gdLst/><a:ahLst/><a:cxnLst/><a:rect l="l" t="t" r="r" b="b"/><a:pathLst><a:path w="3703093" h="2520287"><a:moveTo><a:pt x="218358" y="0"/></a:moveTo><a:lnTo><a:pt x="3484735" y="0"/></a:lnTo><a:cubicBezTo><a:pt x="3605250" y="0"/><a:pt x="3703093" y="97843"/><a:pt x="3703093" y="218358"/></a:cubicBezTo><a:lnTo><a:pt x="3703093" y="2301929"/></a:lnTo><a:cubicBezTo><a:pt x="3703093" y="2422444"/><a:pt x="3605250" y="2520287"/><a:pt x="3484735" y="2520287"/></a:cubicBezTo><a:lnTo><a:pt x="218358" y="2520287"/></a:lnTo><a:cubicBezTo><a:pt x="97843" y="2520287"/><a:pt x="0" y="2422444"/><a:pt x="0" y="2301929"/></a:cubicBezTo><a:lnTo><a:pt x="0" y="218358"/></a:lnTo><a:cubicBezTo><a:pt x="0" y="97843"/><a:pt x="97843" y="0"/><a:pt x="218358" y="0"/></a:cubicBezTo><a:close/></a:path></a:pathLst></a:custGeom><a:solidFill><a:srgbClr val="FFFFFF"/></a:solidFill><a:ln/><a:effectLst><a:outerShdw blurRad="136478" dist="90985" dir="5400000" algn="bl" rotWithShape="0"><a:srgbClr val="000000"><a:alpha val="7843"/></a:srgbClr></a:outerShdw></a:effectLst></p:spPr><p:txBody><a:bodyPr/><a:lstStyle/><a:p><a:endParaRPr lang="en-US"/></a:p></p:txBody></p:sp><p:sp><p:nvSpPr><p:cNvPr id="20" name="Shape 18"/><p:cNvSpPr/><p:nvPr/></p:nvSpPr><p:spPr><a:xfrm><a:off x="8349018" y="1856096"/><a:ext cx="582304" cy="582304"/></a:xfrm><a:custGeom><a:avLst/><a:gdLst/><a:ahLst/><a:cxnLst/><a:rect l="l" t="t" r="r" b="b"/><a:pathLst><a:path w="582304" h="582304"><a:moveTo><a:pt x="145576" y="0"/></a:moveTo><a:lnTo><a:pt x="436728" y="0"/></a:lnTo><a:cubicBezTo><a:pt x="517074" y="0"/><a:pt x="582304" y="65230"/><a:pt x="582304" y="145576"/></a:cubicBezTo><a:lnTo><a:pt x="582304" y="436728"/></a:lnTo><a:cubicBezTo><a:pt x="582304" y="517074"/><a:pt x="517074" y="582304"/><a:pt x="436728" y="582304"/></a:cubicBezTo><a:lnTo><a:pt x="145576" y="582304"/></a:lnTo><a:cubicBezTo><a:pt x="65230" y="582304"/><a:pt x="0" y="517074"/><a:pt x="0" y="436728"/></a:cubicBezTo><a:lnTo><a:pt x="0" y="145576"/></a:lnTo><a:cubicBezTo><a:pt x="0" y="65230"/><a:pt x="65230" y="0"/><a:pt x="145576" y="0"/></a:cubicBezTo><a:close/></a:path></a:pathLst></a:custGeom><a:solidFill><a:srgbClr val="A1887F"/></a:solidFill><a:ln/><a:effectLst><a:outerShdw blurRad="136478" dist="90985" dir="5400000" algn="bl" rotWithShape="0"><a:srgbClr val="000000"><a:alpha val="10196"/></a:srgbClr></a:outerShdw></a:effectLst></p:spPr><p:txBody><a:bodyPr/><a:lstStyle/><a:p><a:endParaRPr lang="en-US"/></a:p></p:txBody></p:sp><p:sp><p:nvSpPr><p:cNvPr id="21" name="Shape 19"/><p:cNvSpPr/><p:nvPr/></p:nvSpPr><p:spPr><a:xfrm><a:off x="8505967" y="2010770"/><a:ext cx="272955" cy="272955"/></a:xfrm><a:custGeom><a:avLst/><a:gdLst/><a:ahLst/><a:cxnLst/><a:rect l="l" t="t" r="r" b="b"/><a:pathLst><a:path w="272955" h="272955"><a:moveTo><a:pt x="272955" y="25590"/></a:moveTo><a:cubicBezTo><a:pt x="272955" y="19672"/><a:pt x="269916" y="14181"/><a:pt x="264852" y="11089"/></a:cubicBezTo><a:cubicBezTo><a:pt x="259787" y="7997"/><a:pt x="253550" y="7677"/><a:pt x="248272" y="10342"/></a:cubicBezTo><a:lnTo><a:pt x="186324" y="41316"/></a:lnTo><a:lnTo><a:pt x="90683" y="9383"/></a:lnTo><a:cubicBezTo><a:pt x="86365" y="7943"/><a:pt x="81727" y="8263"/><a:pt x="77675" y="10289"/></a:cubicBezTo><a:lnTo><a:pt x="9436" y="44409"/></a:lnTo><a:cubicBezTo><a:pt x="3625" y="47341"/><a:pt x="0" y="53258"/><a:pt x="0" y="59709"/></a:cubicBezTo><a:lnTo><a:pt x="0" y="247366"/></a:lnTo><a:cubicBezTo><a:pt x="0" y="253283"/><a:pt x="3039" y="258774"/><a:pt x="8103" y="261866"/></a:cubicBezTo><a:cubicBezTo><a:pt x="13168" y="264958"/><a:pt x="19405" y="265278"/><a:pt x="24683" y="262613"/></a:cubicBezTo><a:lnTo><a:pt x="86578" y="231639"/></a:lnTo><a:lnTo><a:pt x="182219" y="263519"/></a:lnTo><a:cubicBezTo><a:pt x="186537" y="264958"/><a:pt x="191175" y="264639"/><a:pt x="195227" y="262613"/></a:cubicBezTo><a:lnTo><a:pt x="263466" y="228493"/></a:lnTo><a:cubicBezTo><a:pt x="269223" y="225615"/><a:pt x="272902" y="219697"/><a:pt x="272902" y="213246"/></a:cubicBezTo><a:lnTo><a:pt x="272902" y="25590"/></a:lnTo><a:close/><a:moveTo><a:pt x="102358" y="200931"/></a:moveTo><a:lnTo><a:pt x="102358" y="49260"/></a:lnTo><a:lnTo><a:pt x="170597" y="72024"/></a:lnTo><a:lnTo><a:pt x="170597" y="223695"/></a:lnTo><a:lnTo><a:pt x="102358" y="200931"/></a:lnTo><a:close/></a:path></a:pathLst></a:custGeom><a:solidFill><a:srgbClr val="FFFFFF"/></a:solidFill><a:ln/></p:spPr><p:txBody><a:bodyPr/><a:lstStyle/><a:p><a:endParaRPr lang="en-US"/></a:p></p:txBody></p:sp><p:sp><p:nvSpPr><p:cNvPr id="22" name="Text 20"/><p:cNvSpPr/><p:nvPr/></p:nvSpPr><p:spPr><a:xfrm><a:off x="8349018" y="2583976"/><a:ext cx="3375546" cy="291152"/></a:xfrm><a:prstGeom prst="rect"><a:avLst/></a:prstGeom><a:noFill/><a:ln/></p:spPr><p:txBody><a:bodyPr wrap="square" lIns="0" tIns="0" rIns="0" bIns="0" rtlCol="0" anchor="ctr"/><a:lstStyle/><a:p><a:pPr><a:lnSpc><a:spcPct val="110000"/></a:lnSpc></a:pPr><a:r><a:rPr lang="en-US" sz="1719" b="1" dirty="0"><a:solidFill><a:srgbClr val="3E3E3C"/></a:solidFill><a:latin typeface="Hedvig Letters Sans" pitchFamily="34" charset="0"/><a:ea typeface="Hedvig Letters Sans" pitchFamily="34" charset="-122"/><a:cs typeface="Hedvig Letters Sans" pitchFamily="34" charset="-120"/></a:rPr><a:t>OpenStreetMap</a:t></a:r><a:endParaRPr lang="en-US" sz="1600" dirty="0"/></a:p></p:txBody></p:sp><p:sp><p:nvSpPr><p:cNvPr id="23" name="Text 21"/><p:cNvSpPr/><p:nvPr/></p:nvSpPr><p:spPr><a:xfrm><a:off x="8349018" y="2984197"/><a:ext cx="3339152" cy="473122"/></a:xfrm><a:prstGeom prst="rect"><a:avLst/></a:prstGeom><a:noFill/><a:ln/></p:spPr><p:txBody><a:bodyPr wrap="square" lIns="0" tIns="0" rIns="0" bIns="0" rtlCol="0" anchor="ctr"/><a:lstStyle/><a:p><a:pPr><a:lnSpc><a:spcPct val="140000"/></a:lnSpc></a:pPr><a:r><a:rPr lang="en-US" sz="1146" dirty="0"><a:solidFill><a:srgbClr val="3E3E3C"><a:alpha val="70000"/></a:srgbClr></a:solidFill><a:latin typeface="Liter" pitchFamily="34" charset="0"/><a:ea typeface="Liter" pitchFamily="34" charset="-122"/><a:cs typeface="Liter" pitchFamily="34" charset="-120"/></a:rPr><a:t>Seamless integration with OSM for accurate geospatial data and city mapping.</a:t></a:r><a:endParaRPr lang="en-US" sz="1600" dirty="0"/></a:p></p:txBody></p:sp><p:sp><p:nvSpPr><p:cNvPr id="24" name="Shape 22"/><p:cNvSpPr/><p:nvPr/></p:nvSpPr><p:spPr><a:xfrm><a:off x="8349018" y="3606535"/><a:ext cx="3266364" cy="7279"/></a:xfrm><a:custGeom><a:avLst/><a:gdLst/><a:ahLst/><a:cxnLst/><a:rect l="l" t="t" r="r" b="b"/><a:pathLst><a:path w="3266364" h="7279"><a:moveTo><a:pt x="0" y="0"/></a:moveTo><a:lnTo><a:pt x="3266364" y="0"/></a:lnTo><a:lnTo><a:pt x="3266364" y="7279"/></a:lnTo><a:lnTo><a:pt x="0" y="7279"/></a:lnTo><a:lnTo><a:pt x="0" y="0"/></a:lnTo><a:close/></a:path></a:pathLst></a:custGeom><a:solidFill><a:srgbClr val="A1887F"><a:alpha val="20000"/></a:srgbClr></a:solidFill><a:ln/></p:spPr><p:txBody><a:bodyPr/><a:lstStyle/><a:p><a:endParaRPr lang="en-US"/></a:p></p:txBody></p:sp><p:sp><p:nvSpPr><p:cNvPr id="25" name="Text 23"/><p:cNvSpPr/><p:nvPr/></p:nvSpPr><p:spPr><a:xfrm><a:off x="8349018" y="3755751"/><a:ext cx="3330054" cy="181970"/></a:xfrm><a:prstGeom prst="rect"><a:avLst/></a:prstGeom><a:noFill/><a:ln/></p:spPr><p:txBody><a:bodyPr wrap="square" lIns="0" tIns="0" rIns="0" bIns="0" rtlCol="0" anchor="ctr"/><a:lstStyle/><a:p><a:pPr><a:lnSpc><a:spcPct val="120000"/></a:lnSpc></a:pPr><a:r><a:rPr lang="en-US" sz="1003" b="1" dirty="0"><a:solidFill><a:srgbClr val="A1887F"/></a:solidFill><a:latin typeface="Liter" pitchFamily="34" charset="0"/><a:ea typeface="Liter" pitchFamily="34" charset="-122"/><a:cs typeface="Liter" pitchFamily="34" charset="-120"/></a:rPr><a:t>✓ Free &amp; scalable</a:t></a:r><a:endParaRPr lang="en-US" sz="1600" dirty="0"/></a:p></p:txBody></p:sp><p:sp><p:nvSpPr><p:cNvPr id="26" name="Shape 24"/><p:cNvSpPr/><p:nvPr/></p:nvSpPr><p:spPr><a:xfrm><a:off x="363940" y="4338056"/><a:ext cx="3703093" cy="2520287"/></a:xfrm><a:custGeom><a:avLst/><a:gdLst/><a:ahLst/><a:cxnLst/><a:rect l="l" t="t" r="r" b="b"/><a:pathLst><a:path w="3703093" h="2520287"><a:moveTo><a:pt x="218358" y="0"/></a:moveTo><a:lnTo><a:pt x="3484735" y="0"/></a:lnTo><a:cubicBezTo><a:pt x="3605250" y="0"/><a:pt x="3703093" y="97843"/><a:pt x="3703093" y="218358"/></a:cubicBezTo><a:lnTo><a:pt x="3703093" y="2301929"/></a:lnTo><a:cubicBezTo><a:pt x="3703093" y="2422444"/><a:pt x="3605250" y="2520287"/><a:pt x="3484735" y="2520287"/></a:cubicBezTo><a:lnTo><a:pt x="218358" y="2520287"/></a:lnTo><a:cubicBezTo><a:pt x="97843" y="2520287"/><a:pt x="0" y="2422444"/><a:pt x="0" y="2301929"/></a:cubicBezTo><a:lnTo><a:pt x="0" y="218358"/></a:lnTo><a:cubicBezTo><a:pt x="0" y="97843"/><a:pt x="97843" y="0"/><a:pt x="218358" y="0"/></a:cubicBezTo><a:close/></a:path></a:pathLst></a:custGeom><a:solidFill><a:srgbClr val="FFFFFF"/></a:solidFill><a:ln/><a:effectLst><a:outerShdw blurRad="136478" dist="90985" dir="5400000" algn="bl" rotWithShape="0"><a:srgbClr val="000000"><a:alpha val="7843"/></a:srgbClr></a:outerShdw></a:effectLst></p:spPr><p:txBody><a:bodyPr/><a:lstStyle/><a:p><a:endParaRPr lang="en-US"/></a:p></p:txBody></p:sp><p:sp><p:nvSpPr><p:cNvPr id="27" name="Shape 25"/><p:cNvSpPr/><p:nvPr/></p:nvSpPr><p:spPr><a:xfrm><a:off x="582304" y="4556420"/><a:ext cx="582304" cy="582304"/></a:xfrm><a:custGeom><a:avLst/><a:gdLst/><a:ahLst/><a:cxnLst/><a:rect l="l" t="t" r="r" b="b"/><a:pathLst><a:path w="582304" h="582304"><a:moveTo><a:pt x="145576" y="0"/></a:moveTo><a:lnTo><a:pt x="436728" y="0"/></a:lnTo><a:cubicBezTo><a:pt x="517074" y="0"/><a:pt x="582304" y="65230"/><a:pt x="582304" y="145576"/></a:cubicBezTo><a:lnTo><a:pt x="582304" y="436728"/></a:lnTo><a:cubicBezTo><a:pt x="582304" y="517074"/><a:pt x="517074" y="582304"/><a:pt x="436728" y="582304"/></a:cubicBezTo><a:lnTo><a:pt x="145576" y="582304"/></a:lnTo><a:cubicBezTo><a:pt x="65230" y="582304"/><a:pt x="0" y="517074"/><a:pt x="0" y="436728"/></a:cubicBezTo><a:lnTo><a:pt x="0" y="145576"/></a:lnTo><a:cubicBezTo><a:pt x="0" y="65230"/><a:pt x="65230" y="0"/><a:pt x="145576" y="0"/></a:cubicBezTo><a:close/></a:path></a:pathLst></a:custGeom><a:gradFill flip="none" rotWithShape="1"><a:gsLst><a:gs pos="0"><a:srgbClr val="4DB6AC"/></a:gs><a:gs pos="100000"><a:srgbClr val="3D9A91"/></a:gs></a:gsLst><a:lin ang="2700000" scaled="1"/></a:gradFill><a:ln/><a:effectLst><a:outerShdw blurRad="54591" dist="36394" dir="5400000" algn="bl" rotWithShape="0"><a:srgbClr val="4DB6AC"><a:alpha val="30196"/></a:srgbClr></a:outerShdw></a:effectLst></p:spPr><p:txBody><a:bodyPr/><a:lstStyle/><a:p><a:endParaRPr lang="en-US"/></a:p></p:txBody></p:sp><p:sp><p:nvSpPr><p:cNvPr id="28" name="Shape 26"/><p:cNvSpPr/><p:nvPr/></p:nvSpPr><p:spPr><a:xfrm><a:off x="739254" y="4711094"/><a:ext cx="272955" cy="272955"/></a:xfrm><a:custGeom><a:avLst/><a:gdLst/><a:ahLst/><a:cxnLst/><a:rect l="l" t="t" r="r" b="b"/><a:pathLst><a:path w="272955" h="272955"><a:moveTo><a:pt x="63974" y="29854"/></a:moveTo><a:cubicBezTo><a:pt x="63974" y="13381"/><a:pt x="77355" y="0"/><a:pt x="93828" y="0"/></a:cubicBezTo><a:lnTo><a:pt x="106623" y="0"/></a:lnTo><a:cubicBezTo><a:pt x="116059" y="0"/><a:pt x="123683" y="7624"/><a:pt x="123683" y="17060"/></a:cubicBezTo><a:lnTo><a:pt x="123683" y="255896"/></a:lnTo><a:cubicBezTo><a:pt x="123683" y="265332"/><a:pt x="116059" y="272955"/><a:pt x="106623" y="272955"/></a:cubicBezTo><a:lnTo><a:pt x="89563" y="272955"/></a:lnTo><a:cubicBezTo><a:pt x="73677" y="272955"/><a:pt x="60295" y="262080"/><a:pt x="56510" y="247366"/></a:cubicBezTo><a:cubicBezTo><a:pt x="56137" y="247366"/><a:pt x="55817" y="247366"/><a:pt x="55444" y="247366"/></a:cubicBezTo><a:cubicBezTo><a:pt x="31880" y="247366"/><a:pt x="12795" y="228280"/><a:pt x="12795" y="204716"/></a:cubicBezTo><a:cubicBezTo><a:pt x="12795" y="195120"/><a:pt x="15993" y="186271"/><a:pt x="21325" y="179127"/></a:cubicBezTo><a:cubicBezTo><a:pt x="10982" y="171343"/><a:pt x="4265" y="158975"/><a:pt x="4265" y="145007"/></a:cubicBezTo><a:cubicBezTo><a:pt x="4265" y="128534"/><a:pt x="13648" y="114193"/><a:pt x="27296" y="107103"/></a:cubicBezTo><a:cubicBezTo><a:pt x="23510" y="100706"/><a:pt x="21325" y="93242"/><a:pt x="21325" y="85299"/></a:cubicBezTo><a:cubicBezTo><a:pt x="21325" y="61735"/><a:pt x="40410" y="42649"/><a:pt x="63974" y="42649"/></a:cubicBezTo><a:lnTo><a:pt x="63974" y="29854"/></a:lnTo><a:close/><a:moveTo><a:pt x="208981" y="29854"/></a:moveTo><a:lnTo><a:pt x="208981" y="42649"/></a:lnTo><a:cubicBezTo><a:pt x="232545" y="42649"/><a:pt x="251631" y="61735"/><a:pt x="251631" y="85299"/></a:cubicBezTo><a:cubicBezTo><a:pt x="251631" y="93295"/><a:pt x="249445" y="100759"/><a:pt x="245660" y="107103"/></a:cubicBezTo><a:cubicBezTo><a:pt x="259361" y="114193"/><a:pt x="268690" y="128481"/><a:pt x="268690" y="145007"/></a:cubicBezTo><a:cubicBezTo><a:pt x="268690" y="158975"/><a:pt x="261973" y="171343"/><a:pt x="251631" y="179127"/></a:cubicBezTo><a:cubicBezTo><a:pt x="256962" y="186271"/><a:pt x="260160" y="195120"/><a:pt x="260160" y="204716"/></a:cubicBezTo><a:cubicBezTo><a:pt x="260160" y="228280"/><a:pt x="241075" y="247366"/><a:pt x="217511" y="247366"/></a:cubicBezTo><a:cubicBezTo><a:pt x="217138" y="247366"/><a:pt x="216818" y="247366"/><a:pt x="216445" y="247366"/></a:cubicBezTo><a:cubicBezTo><a:pt x="212660" y="262080"/><a:pt x="199279" y="272955"/><a:pt x="183392" y="272955"/></a:cubicBezTo><a:lnTo><a:pt x="166332" y="272955"/></a:lnTo><a:cubicBezTo><a:pt x="156896" y="272955"/><a:pt x="149272" y="265332"/><a:pt x="149272" y="255896"/></a:cubicBezTo><a:lnTo><a:pt x="149272" y="17060"/></a:lnTo><a:cubicBezTo><a:pt x="149272" y="7624"/><a:pt x="156896" y="0"/><a:pt x="166332" y="0"/></a:cubicBezTo><a:lnTo><a:pt x="179127" y="0"/></a:lnTo><a:cubicBezTo><a:pt x="195600" y="0"/><a:pt x="208981" y="13381"/><a:pt x="208981" y="29854"/></a:cubicBezTo><a:close/></a:path></a:pathLst></a:custGeom><a:solidFill><a:srgbClr val="FFFFFF"/></a:solidFill><a:ln/></p:spPr><p:txBody><a:bodyPr/><a:lstStyle/><a:p><a:endParaRPr lang="en-US"/></a:p></p:txBody></p:sp><p:sp><p:nvSpPr><p:cNvPr id="29" name="Text 27"/><p:cNvSpPr/><p:nvPr/></p:nvSpPr><p:spPr><a:xfrm><a:off x="582304" y="5284300"/><a:ext cx="3375546" cy="291152"/></a:xfrm><a:prstGeom prst="rect"><a:avLst/></a:prstGeom><a:noFill/><a:ln/></p:spPr><p:txBody><a:bodyPr wrap="square" lIns="0" tIns="0" rIns="0" bIns="0" rtlCol="0" anchor="ctr"/><a:lstStyle/><a:p><a:pPr><a:lnSpc><a:spcPct val="110000"/></a:lnSpc></a:pPr><a:r><a:rPr lang="en-US" sz="1719" b="1" dirty="0"><a:solidFill><a:srgbClr val="3E3E3C"/></a:solidFill><a:latin typeface="Hedvig Letters Sans" pitchFamily="34" charset="0"/><a:ea typeface="Hedvig Letters Sans" pitchFamily="34" charset="-122"/><a:cs typeface="Hedvig Letters Sans" pitchFamily="34" charset="-120"/></a:rPr><a:t>RAG-Based AI</a:t></a:r><a:endParaRPr lang="en-US" sz="1600" dirty="0"/></a:p></p:txBody></p:sp><p:sp><p:nvSpPr><p:cNvPr id="30" name="Text 28"/><p:cNvSpPr/><p:nvPr/></p:nvSpPr><p:spPr><a:xfrm><a:off x="582304" y="5684521"/><a:ext cx="3339152" cy="473122"/></a:xfrm><a:prstGeom prst="rect"><a:avLst/></a:prstGeom><a:noFill/><a:ln/></p:spPr><p:txBody><a:bodyPr wrap="square" lIns="0" tIns="0" rIns="0" bIns="0" rtlCol="0" anchor="ctr"/><a:lstStyle/><a:p><a:pPr><a:lnSpc><a:spcPct val="140000"/></a:lnSpc></a:pPr><a:r><a:rPr lang="en-US" sz="1146" dirty="0"><a:solidFill><a:srgbClr val="3E3E3C"><a:alpha val="70000"/></a:srgbClr></a:solidFill><a:latin typeface="Liter" pitchFamily="34" charset="0"/><a:ea typeface="Liter" pitchFamily="34" charset="-122"/><a:cs typeface="Liter" pitchFamily="34" charset="-120"/></a:rPr><a:t>Retrieval-Augmented Generation for context-aware policy recommendations.</a:t></a:r><a:endParaRPr lang="en-US" sz="1600" dirty="0"/></a:p></p:txBody></p:sp><p:sp><p:nvSpPr><p:cNvPr id="31" name="Shape 29"/><p:cNvSpPr/><p:nvPr/></p:nvSpPr><p:spPr><a:xfrm><a:off x="582304" y="6306859"/><a:ext cx="3266364" cy="7279"/></a:xfrm><a:custGeom><a:avLst/><a:gdLst/><a:ahLst/><a:cxnLst/><a:rect l="l" t="t" r="r" b="b"/><a:pathLst><a:path w="3266364" h="7279"><a:moveTo><a:pt x="0" y="0"/></a:moveTo><a:lnTo><a:pt x="3266364" y="0"/></a:lnTo><a:lnTo><a:pt x="3266364" y="7279"/></a:lnTo><a:lnTo><a:pt x="0" y="7279"/></a:lnTo><a:lnTo><a:pt x="0" y="0"/></a:lnTo><a:close/></a:path></a:pathLst></a:custGeom><a:solidFill><a:srgbClr val="4DB6AC"><a:alpha val="20000"/></a:srgbClr></a:solidFill><a:ln/></p:spPr><p:txBody><a:bodyPr/><a:lstStyle/><a:p><a:endParaRPr lang="en-US"/></a:p></p:txBody></p:sp><p:sp><p:nvSpPr><p:cNvPr id="32" name="Text 30"/><p:cNvSpPr/><p:nvPr/></p:nvSpPr><p:spPr><a:xfrm><a:off x="582304" y="6456073"/><a:ext cx="3330054" cy="181970"/></a:xfrm><a:prstGeom prst="rect"><a:avLst/></a:prstGeom><a:noFill/><a:ln/></p:spPr><p:txBody><a:bodyPr wrap="square" lIns="0" tIns="0" rIns="0" bIns="0" rtlCol="0" anchor="ctr"/><a:lstStyle/><a:p><a:pPr><a:lnSpc><a:spcPct val="120000"/></a:lnSpc></a:pPr><a:r><a:rPr lang="en-US" sz="1003" b="1" dirty="0"><a:solidFill><a:srgbClr val="4DB6AC"/></a:solidFill><a:latin typeface="Liter" pitchFamily="34" charset="0"/><a:ea typeface="Liter" pitchFamily="34" charset="-122"/><a:cs typeface="Liter" pitchFamily="34" charset="-120"/></a:rPr><a:t>✓ Grounded in real data</a:t></a:r><a:endParaRPr lang="en-US" sz="1600" dirty="0"/></a:p></p:txBody></p:sp><p:sp><p:nvSpPr><p:cNvPr id="33" name="Shape 31"/><p:cNvSpPr/><p:nvPr/></p:nvSpPr><p:spPr><a:xfrm><a:off x="4247297" y="4338056"/><a:ext cx="3703093" cy="2520287"/></a:xfrm><a:custGeom><a:avLst/><a:gdLst/><a:ahLst/><a:cxnLst/><a:rect l="l" t="t" r="r" b="b"/><a:pathLst><a:path w="3703093" h="2520287"><a:moveTo><a:pt x="218358" y="0"/></a:moveTo><a:lnTo><a:pt x="3484735" y="0"/></a:lnTo><a:cubicBezTo><a:pt x="3605250" y="0"/><a:pt x="3703093" y="97843"/><a:pt x="3703093" y="218358"/></a:cubicBezTo><a:lnTo><a:pt x="3703093" y="2301929"/></a:lnTo><a:cubicBezTo><a:pt x="3703093" y="2422444"/><a:pt x="3605250" y="2520287"/><a:pt x="3484735" y="2520287"/></a:cubicBezTo><a:lnTo><a:pt x="218358" y="2520287"/></a:lnTo><a:cubicBezTo><a:pt x="97843" y="2520287"/><a:pt x="0" y="2422444"/><a:pt x="0" y="2301929"/></a:cubicBezTo><a:lnTo><a:pt x="0" y="218358"/></a:lnTo><a:cubicBezTo><a:pt x="0" y="97843"/><a:pt x="97843" y="0"/><a:pt x="218358" y="0"/></a:cubicBezTo><a:close/></a:path></a:pathLst></a:custGeom><a:solidFill><a:srgbClr val="FFFFFF"/></a:solidFill><a:ln/><a:effectLst><a:outerShdw blurRad="136478" dist="90985" dir="5400000" algn="bl" rotWithShape="0"><a:srgbClr val="000000"><a:alpha val="7843"/></a:srgbClr></a:outerShdw></a:effectLst></p:spPr><p:txBody><a:bodyPr/><a:lstStyle/><a:p><a:endParaRPr lang="en-US"/></a:p></p:txBody></p:sp><p:sp><p:nvSpPr><p:cNvPr id="34" name="Shape 32"/><p:cNvSpPr/><p:nvPr/></p:nvSpPr><p:spPr><a:xfrm><a:off x="4465661" y="4556420"/><a:ext cx="582304" cy="582304"/></a:xfrm><a:custGeom><a:avLst/><a:gdLst/><a:ahLst/><a:cxnLst/><a:rect l="l" t="t" r="r" b="b"/><a:pathLst><a:path w="582304" h="582304"><a:moveTo><a:pt x="145576" y="0"/></a:moveTo><a:lnTo><a:pt x="436728" y="0"/></a:lnTo><a:cubicBezTo><a:pt x="517074" y="0"/><a:pt x="582304" y="65230"/><a:pt x="582304" y="145576"/></a:cubicBezTo><a:lnTo><a:pt x="582304" y="436728"/></a:lnTo><a:cubicBezTo><a:pt x="582304" y="517074"/><a:pt x="517074" y="582304"/><a:pt x="436728" y="582304"/></a:cubicBezTo><a:lnTo><a:pt x="145576" y="582304"/></a:lnTo><a:cubicBezTo><a:pt x="65230" y="582304"/><a:pt x="0" y="517074"/><a:pt x="0" y="436728"/></a:cubicBezTo><a:lnTo><a:pt x="0" y="145576"/></a:lnTo><a:cubicBezTo><a:pt x="0" y="65230"/><a:pt x="65230" y="0"/><a:pt x="145576" y="0"/></a:cubicBezTo><a:close/></a:path></a:pathLst></a:custGeom><a:solidFill><a:srgbClr val="FFB74D"/></a:solidFill><a:ln/><a:effectLst><a:outerShdw blurRad="136478" dist="90985" dir="5400000" algn="bl" rotWithShape="0"><a:srgbClr val="000000"><a:alpha val="10196"/></a:srgbClr></a:outerShdw></a:effectLst></p:spPr><p:txBody><a:bodyPr/><a:lstStyle/><a:p><a:endParaRPr lang="en-US"/></a:p></p:txBody></p:sp><p:sp><p:nvSpPr><p:cNvPr id="35" name="Shape 33"/><p:cNvSpPr/><p:nvPr/></p:nvSpPr><p:spPr><a:xfrm><a:off x="4605551" y="4711094"/><a:ext cx="307075" cy="272955"/></a:xfrm><a:custGeom><a:avLst/><a:gdLst/><a:ahLst/><a:cxnLst/><a:rect l="l" t="t" r="r" b="b"/><a:pathLst><a:path w="307075" h="272955"><a:moveTo><a:pt x="51179" y="0"/></a:moveTo><a:cubicBezTo><a:pt x="32360" y="0"/><a:pt x="17060" y="15300"/><a:pt x="17060" y="34119"/></a:cubicBezTo><a:lnTo><a:pt x="17060" y="238836"/></a:lnTo><a:cubicBezTo><a:pt x="17060" y="257655"/><a:pt x="32360" y="272955"/><a:pt x="51179" y="272955"/></a:cubicBezTo><a:lnTo><a:pt x="93828" y="272955"/></a:lnTo><a:lnTo><a:pt x="93828" y="213246"/></a:lnTo><a:cubicBezTo><a:pt x="93828" y="194427"/><a:pt x="109129" y="179127"/><a:pt x="127948" y="179127"/></a:cubicBezTo><a:lnTo><a:pt x="221776" y="179127"/></a:lnTo><a:lnTo><a:pt x="221776" y="90896"/></a:lnTo><a:cubicBezTo><a:pt x="221776" y="81833"/><a:pt x="218204" y="73143"/><a:pt x="211807" y="66746"/></a:cubicBezTo><a:lnTo><a:pt x="154977" y="9969"/></a:lnTo><a:cubicBezTo><a:pt x="148579" y="3572"/><a:pt x="139943" y="0"/><a:pt x="130880" y="0"/></a:cubicBezTo><a:lnTo><a:pt x="51179" y="0"/></a:lnTo><a:close/><a:moveTo><a:pt x="190589" y="93828"/></a:moveTo><a:lnTo><a:pt x="140743" y="93828"/></a:lnTo><a:cubicBezTo><a:pt x="133652" y="93828"/><a:pt x="127948" y="88124"/><a:pt x="127948" y="81034"/></a:cubicBezTo><a:lnTo><a:pt x="127948" y="31187"/></a:lnTo><a:lnTo><a:pt x="190589" y="93828"/></a:lnTo><a:close/><a:moveTo><a:pt x="127948" y="202584"/></a:moveTo><a:cubicBezTo><a:pt x="122083" y="202584"/><a:pt x="117285" y="207382"/><a:pt x="117285" y="213246"/></a:cubicBezTo><a:lnTo><a:pt x="117285" y="281485"/></a:lnTo><a:cubicBezTo><a:pt x="117285" y="287349"/><a:pt x="122083" y="292147"/><a:pt x="127948" y="292147"/></a:cubicBezTo><a:cubicBezTo><a:pt x="133812" y="292147"/><a:pt x="138610" y="287349"/><a:pt x="138610" y="281485"/></a:cubicBezTo><a:lnTo><a:pt x="138610" y="266558"/></a:lnTo><a:lnTo><a:pt x="145007" y="266558"/></a:lnTo><a:cubicBezTo><a:pt x="162654" y="266558"/><a:pt x="176994" y="252217"/><a:pt x="176994" y="234571"/></a:cubicBezTo><a:cubicBezTo><a:pt x="176994" y="216925"/><a:pt x="162654" y="202584"/><a:pt x="145007" y="202584"/></a:cubicBezTo><a:lnTo><a:pt x="127948" y="202584"/></a:lnTo><a:close/><a:moveTo><a:pt x="145007" y="245233"/></a:moveTo><a:lnTo><a:pt x="138610" y="245233"/></a:lnTo><a:lnTo><a:pt x="138610" y="223909"/></a:lnTo><a:lnTo><a:pt x="145007" y="223909"/></a:lnTo><a:cubicBezTo><a:pt x="150872" y="223909"/><a:pt x="155670" y="228707"/><a:pt x="155670" y="234571"/></a:cubicBezTo><a:cubicBezTo><a:pt x="155670" y="240435"/><a:pt x="150872" y="245233"/><a:pt x="145007" y="245233"/></a:cubicBezTo><a:close/><a:moveTo><a:pt x="196187" y="202584"/></a:moveTo><a:cubicBezTo><a:pt x="190322" y="202584"/><a:pt x="185524" y="207382"/><a:pt x="185524" y="213246"/></a:cubicBezTo><a:lnTo><a:pt x="185524" y="281485"/></a:lnTo><a:cubicBezTo><a:pt x="185524" y="287349"/><a:pt x="190322" y="292147"/><a:pt x="196187" y="292147"/></a:cubicBezTo><a:lnTo><a:pt x="213246" y="292147"/></a:lnTo><a:cubicBezTo><a:pt x="228547" y="292147"/><a:pt x="240968" y="279726"/><a:pt x="240968" y="264425"/></a:cubicBezTo><a:lnTo><a:pt x="240968" y="230306"/></a:lnTo><a:cubicBezTo><a:pt x="240968" y="215006"/><a:pt x="228547" y="202584"/><a:pt x="213246" y="202584"/></a:cubicBezTo><a:lnTo><a:pt x="196187" y="202584"/></a:lnTo><a:close/><a:moveTo><a:pt x="206849" y="270823"/></a:moveTo><a:lnTo><a:pt x="206849" y="223909"/></a:lnTo><a:lnTo><a:pt x="213246" y="223909"/></a:lnTo><a:cubicBezTo><a:pt x="216765" y="223909"/><a:pt x="219644" y="226787"/><a:pt x="219644" y="230306"/></a:cubicBezTo><a:lnTo><a:pt x="219644" y="264425"/></a:lnTo><a:cubicBezTo><a:pt x="219644" y="267944"/><a:pt x="216765" y="270823"/><a:pt x="213246" y="270823"/></a:cubicBezTo><a:lnTo><a:pt x="206849" y="270823"/></a:lnTo><a:close/><a:moveTo><a:pt x="253763" y="213246"/></a:moveTo><a:lnTo><a:pt x="253763" y="281485"/></a:lnTo><a:cubicBezTo><a:pt x="253763" y="287349"/><a:pt x="258561" y="292147"/><a:pt x="264425" y="292147"/></a:cubicBezTo><a:cubicBezTo><a:pt x="270290" y="292147"/><a:pt x="275088" y="287349"/><a:pt x="275088" y="281485"/></a:cubicBezTo><a:lnTo><a:pt x="275088" y="258028"/></a:lnTo><a:lnTo><a:pt x="290015" y="258028"/></a:lnTo><a:cubicBezTo><a:pt x="295879" y="258028"/><a:pt x="300677" y="253230"/><a:pt x="300677" y="247366"/></a:cubicBezTo><a:cubicBezTo><a:pt x="300677" y="241501"/><a:pt x="295879" y="236703"/><a:pt x="290015" y="236703"/></a:cubicBezTo><a:lnTo><a:pt x="275088" y="236703"/></a:lnTo><a:lnTo><a:pt x="275088" y="223909"/></a:lnTo><a:lnTo><a:pt x="290015" y="223909"/></a:lnTo><a:cubicBezTo><a:pt x="295879" y="223909"/><a:pt x="300677" y="219111"/><a:pt x="300677" y="213246"/></a:cubicBezTo><a:cubicBezTo><a:pt x="300677" y="207382"/><a:pt x="295879" y="202584"/><a:pt x="290015" y="202584"/></a:cubicBezTo><a:lnTo><a:pt x="264425" y="202584"/></a:lnTo><a:cubicBezTo><a:pt x="258561" y="202584"/><a:pt x="253763" y="207382"/><a:pt x="253763" y="213246"/></a:cubicBezTo><a:close/></a:path></a:pathLst></a:custGeom><a:solidFill><a:srgbClr val="FFFFFF"/></a:solidFill><a:ln/></p:spPr><p:txBody><a:bodyPr/><a:lstStyle/><a:p><a:endParaRPr lang="en-US"/></a:p></p:txBody></p:sp><p:sp><p:nvSpPr><p:cNvPr id="36" name="Text 34"/><p:cNvSpPr/><p:nvPr/></p:nvSpPr><p:spPr><a:xfrm><a:off x="4465661" y="5284300"/><a:ext cx="3375546" cy="291152"/></a:xfrm><a:prstGeom prst="rect"><a:avLst/></a:prstGeom><a:noFill/><a:ln/></p:spPr><p:txBody><a:bodyPr wrap="square" lIns="0" tIns="0" rIns="0" bIns="0" rtlCol="0" anchor="ctr"/><a:lstStyle/><a:p><a:pPr><a:lnSpc><a:spcPct val="110000"/></a:lnSpc></a:pPr><a:r><a:rPr lang="en-US" sz="1719" b="1" dirty="0"><a:solidFill><a:srgbClr val="3E3E3C"/></a:solidFill><a:latin typeface="Hedvig Letters Sans" pitchFamily="34" charset="0"/><a:ea typeface="Hedvig Letters Sans" pitchFamily="34" charset="-122"/><a:cs typeface="Hedvig Letters Sans" pitchFamily="34" charset="-120"/></a:rPr><a:t>PDF Reports</a:t></a:r><a:endParaRPr lang="en-US" sz="1600" dirty="0"/></a:p></p:txBody></p:sp><p:sp><p:nvSpPr><p:cNvPr id="37" name="Text 35"/><p:cNvSpPr/><p:nvPr/></p:nvSpPr><p:spPr><a:xfrm><a:off x="4465661" y="5684521"/><a:ext cx="3339152" cy="473122"/></a:xfrm><a:prstGeom prst="rect"><a:avLst/></a:prstGeom><a:noFill/><a:ln/></p:spPr><p:txBody><a:bodyPr wrap="square" lIns="0" tIns="0" rIns="0" bIns="0" rtlCol="0" anchor="ctr"/><a:lstStyle/><a:p><a:pPr><a:lnSpc><a:spcPct val="140000"/></a:lnSpc></a:pPr><a:r><a:rPr lang="en-US" sz="1146" dirty="0"><a:solidFill><a:srgbClr val="3E3E3C"><a:alpha val="70000"/></a:srgbClr></a:solidFill><a:latin typeface="Liter" pitchFamily="34" charset="0"/><a:ea typeface="Liter" pitchFamily="34" charset="-122"/><a:cs typeface="Liter" pitchFamily="34" charset="-120"/></a:rPr><a:t>One-click generation of comprehensive, shareable reports for stakeholders.</a:t></a:r><a:endParaRPr lang="en-US" sz="1600" dirty="0"/></a:p></p:txBody></p:sp><p:sp><p:nvSpPr><p:cNvPr id="38" name="Shape 36"/><p:cNvSpPr/><p:nvPr/></p:nvSpPr><p:spPr><a:xfrm><a:off x="4465661" y="6306859"/><a:ext cx="3266364" cy="7279"/></a:xfrm><a:custGeom><a:avLst/><a:gdLst/><a:ahLst/><a:cxnLst/><a:rect l="l" t="t" r="r" b="b"/><a:pathLst><a:path w="3266364" h="7279"><a:moveTo><a:pt x="0" y="0"/></a:moveTo><a:lnTo><a:pt x="3266364" y="0"/></a:lnTo><a:lnTo><a:pt x="3266364" y="7279"/></a:lnTo><a:lnTo><a:pt x="0" y="7279"/></a:lnTo><a:lnTo><a:pt x="0" y="0"/></a:lnTo><a:close/></a:path></a:pathLst></a:custGeom><a:solidFill><a:srgbClr val="FFB74D"><a:alpha val="20000"/></a:srgbClr></a:solidFill><a:ln/></p:spPr><p:txBody><a:bodyPr/><a:lstStyle/><a:p><a:endParaRPr lang="en-US"/></a:p></p:txBody></p:sp><p:sp><p:nvSpPr><p:cNvPr id="39" name="Text 37"/><p:cNvSpPr/><p:nvPr/></p:nvSpPr><p:spPr><a:xfrm><a:off x="4465661" y="6456073"/><a:ext cx="3330054" cy="181970"/></a:xfrm><a:prstGeom prst="rect"><a:avLst/></a:prstGeom><a:noFill/><a:ln/></p:spPr><p:txBody><a:bodyPr wrap="square" lIns="0" tIns="0" rIns="0" bIns="0" rtlCol="0" anchor="ctr"/><a:lstStyle/><a:p><a:pPr><a:lnSpc><a:spcPct val="120000"/></a:lnSpc></a:pPr><a:r><a:rPr lang="en-US" sz="1003" b="1" dirty="0"><a:solidFill><a:srgbClr val="FFB74D"/></a:solidFill><a:latin typeface="Liter" pitchFamily="34" charset="0"/><a:ea typeface="Liter" pitchFamily="34" charset="-122"/><a:cs typeface="Liter" pitchFamily="34" charset="-120"/></a:rPr><a:t>✓ Instant documentation</a:t></a:r><a:endParaRPr lang="en-US" sz="1600" dirty="0"/></a:p></p:txBody></p:sp><p:sp><p:nvSpPr><p:cNvPr id="40" name="Shape 38"/><p:cNvSpPr/><p:nvPr/></p:nvSpPr><p:spPr><a:xfrm><a:off x="8130654" y="4338056"/><a:ext cx="3703093" cy="2520287"/></a:xfrm><a:custGeom><a:avLst/><a:gdLst/><a:ahLst/><a:cxnLst/><a:rect l="l" t="t" r="r" b="b"/><a:pathLst><a:path w="3703093" h="2520287"><a:moveTo><a:pt x="145572" y="0"/></a:moveTo><a:lnTo><a:pt x="3557521" y="0"/></a:lnTo><a:cubicBezTo><a:pt x="3637918" y="0"/><a:pt x="3703093" y="65175"/><a:pt x="3703093" y="145572"/></a:cubicBezTo><a:lnTo><a:pt x="3703093" y="2374715"/></a:lnTo><a:cubicBezTo><a:pt x="3703093" y="2455112"/><a:pt x="3637918" y="2520287"/><a:pt x="3557521" y="2520287"/></a:cubicBezTo><a:lnTo><a:pt x="145572" y="2520287"/></a:lnTo><a:cubicBezTo><a:pt x="65175" y="2520287"/><a:pt x="0" y="2455112"/><a:pt x="0" y="2374715"/></a:cubicBezTo><a:lnTo><a:pt x="0" y="145572"/></a:lnTo><a:cubicBezTo><a:pt x="0" y="65175"/><a:pt x="65175" y="0"/><a:pt x="145572" y="0"/></a:cubicBezTo><a:close/></a:path></a:pathLst></a:custGeom><a:gradFill flip="none" rotWithShape="1"><a:gsLst><a:gs pos="0"><a:srgbClr val="FFB74D"/></a:gs><a:gs pos="100000"><a:srgbClr val="FFA726"/></a:gs></a:gsLst><a:lin ang="2700000" scaled="1"/></a:gradFill><a:ln/><a:effectLst><a:outerShdw blurRad="54591" dist="36394" dir="5400000" algn="bl" rotWithShape="0"><a:srgbClr val="FFB74D"><a:alpha val="30196"/></a:srgbClr></a:outerShdw></a:effectLst></p:spPr><p:txBody><a:bodyPr/><a:lstStyle/><a:p><a:endParaRPr lang="en-US"/></a:p></p:txBody></p:sp><p:sp><p:nvSpPr><p:cNvPr id="41" name="Shape 39"/><p:cNvSpPr/><p:nvPr/></p:nvSpPr><p:spPr><a:xfrm><a:off x="9817517" y="4644106"/><a:ext cx="327546" cy="436728"/></a:xfrm><a:custGeom><a:avLst/><a:gdLst/><a:ahLst/><a:cxnLst/><a:rect l="l" t="t" r="r" b="b"/><a:pathLst><a:path w="327546" h="436728"><a:moveTo><a:pt x="249839" y="327546"/></a:moveTo><a:cubicBezTo><a:pt x="256066" y="308525"/><a:pt x="268520" y="291294"/><a:pt x="282594" y="276452"/></a:cubicBezTo><a:cubicBezTo><a:pt x="310487" y="247110"/><a:pt x="327546" y="207446"/><a:pt x="327546" y="163773"/></a:cubicBezTo><a:cubicBezTo><a:pt x="327546" y="73357"/><a:pt x="254190" y="0"/><a:pt x="163773" y="0"/></a:cubicBezTo><a:cubicBezTo><a:pt x="73357" y="0"/><a:pt x="0" y="73357"/><a:pt x="0" y="163773"/></a:cubicBezTo><a:cubicBezTo><a:pt x="0" y="207446"/><a:pt x="17060" y="247110"/><a:pt x="44952" y="276452"/></a:cubicBezTo><a:cubicBezTo><a:pt x="59027" y="291294"/><a:pt x="71565" y="308525"/><a:pt x="77707" y="327546"/></a:cubicBezTo><a:lnTo><a:pt x="249754" y="327546"/></a:lnTo><a:close/><a:moveTo><a:pt x="245660" y="368490"/></a:moveTo><a:lnTo><a:pt x="81887" y="368490"/></a:lnTo><a:lnTo><a:pt x="81887" y="382137"/></a:lnTo><a:cubicBezTo><a:pt x="81887" y="419839"/><a:pt x="112423" y="450376"/><a:pt x="150125" y="450376"/></a:cubicBezTo><a:lnTo><a:pt x="177421" y="450376"/></a:lnTo><a:cubicBezTo><a:pt x="215123" y="450376"/><a:pt x="245660" y="419839"/><a:pt x="245660" y="382137"/></a:cubicBezTo><a:lnTo><a:pt x="245660" y="368490"/></a:lnTo><a:close/><a:moveTo><a:pt x="156949" y="95534"/></a:moveTo><a:cubicBezTo><a:pt x="123000" y="95534"/><a:pt x="95534" y="123000"/><a:pt x="95534" y="156949"/></a:cubicBezTo><a:cubicBezTo><a:pt x="95534" y="168294"/><a:pt x="86407" y="177421"/><a:pt x="75063" y="177421"/></a:cubicBezTo><a:cubicBezTo><a:pt x="63718" y="177421"/><a:pt x="54591" y="168294"/><a:pt x="54591" y="156949"/></a:cubicBezTo><a:cubicBezTo><a:pt x="54591" y="100396"/><a:pt x="100396" y="54591"/><a:pt x="156949" y="54591"/></a:cubicBezTo><a:cubicBezTo><a:pt x="168294" y="54591"/><a:pt x="177421" y="63718"/><a:pt x="177421" y="75063"/></a:cubicBezTo><a:cubicBezTo><a:pt x="177421" y="86407"/><a:pt x="168294" y="95534"/><a:pt x="156949" y="95534"/></a:cubicBezTo><a:close/></a:path></a:pathLst></a:custGeom><a:solidFill><a:srgbClr val="FFFFFF"/></a:solidFill><a:ln/></p:spPr><p:txBody><a:bodyPr/><a:lstStyle/><a:p><a:endParaRPr lang="en-US"/></a:p></p:txBody></p:sp><p:sp><p:nvSpPr><p:cNvPr id="42" name="Text 40"/><p:cNvSpPr/><p:nvPr/></p:nvSpPr><p:spPr><a:xfrm><a:off x="9334387" y="5226411"/><a:ext cx="1291988" cy="327546"/></a:xfrm><a:prstGeom prst="rect"><a:avLst/></a:prstGeom><a:noFill/><a:ln/></p:spPr><p:txBody><a:bodyPr wrap="square" lIns="0" tIns="0" rIns="0" bIns="0" rtlCol="0" anchor="ctr"/><a:lstStyle/><a:p><a:pPr algn="ctr"><a:lnSpc><a:spcPct val="100000"/></a:lnSpc></a:pPr><a:r><a:rPr lang="en-US" sz="2149" b="1" dirty="0"><a:solidFill><a:srgbClr val="FFFFFF"/></a:solidFill><a:latin typeface="Hedvig Letters Sans" pitchFamily="34" charset="0"/><a:ea typeface="Hedvig Letters Sans" pitchFamily="34" charset="-122"/><a:cs typeface="Hedvig Letters Sans" pitchFamily="34" charset="-120"/></a:rPr><a:t>Highlight</a:t></a:r><a:endParaRPr lang="en-US" sz="1600" dirty="0"/></a:p></p:txBody></p:sp><p:sp><p:nvSpPr><p:cNvPr id="43" name="Text 41"/><p:cNvSpPr/><p:nvPr/></p:nvSpPr><p:spPr><a:xfrm><a:off x="8303525" y="5663139"/><a:ext cx="3357349" cy="891654"/></a:xfrm><a:prstGeom prst="rect"><a:avLst/></a:prstGeom><a:noFill/><a:ln/></p:spPr><p:txBody><a:bodyPr wrap="square" lIns="0" tIns="0" rIns="0" bIns="0" rtlCol="0" anchor="ctr"/><a:lstStyle/><a:p><a:pPr algn="ctr"><a:lnSpc><a:spcPct val="140000"/></a:lnSpc></a:pPr><a:r><a:rPr lang="en-US" sz="1433" b="1" dirty="0"><a:solidFill><a:srgbClr val="FFFFFF"/></a:solidFill><a:latin typeface="Liter" pitchFamily="34" charset="0"/><a:ea typeface="Liter" pitchFamily="34" charset="-122"/><a:cs typeface="Liter" pitchFamily="34" charset="-120"/></a:rPr><a:t>Not just chatbot → Visual + Analytical AI combining conversation with powerful data visualization</a:t></a:r><a:endParaRPr lang="en-US" sz="1600" dirty="0"/></a:p></p:txBody></p:sp></p:spTree></p:cSld><p:clrMapOvr><a:masterClrMapping/></p:clrMapOvr><p:transition><p:fade/></p:transition></p:sld>